LICENSE.txt
setup.py
pytorch_tutorials/__init__.py
pytorch_tutorials.egg-info/PKG-INFO
pytorch_tutorials.egg-info/SOURCES.txt
pytorch_tutorials.egg-info/dependency_links.txt
pytorch_tutorials.egg-info/requires.txt
pytorch_tutorials.egg-info/top_level.txt
pytorch_tutorials/intro_to_computer_vision/__init__.py
pytorch_tutorials/intro_to_computer_vision/cv_datasets.py
pytorch_tutorials/intro_to_computer_vision/cv_models.py
pytorch_tutorials/intro_to_computer_vision/cv_pl_data_modules.py
pytorch_tutorials/intro_to_computer_vision/cv_utility.py